Booth algorithm/booth_controller.v
module booth_controller(
 input clk,
 input start,
 input q0,
 input qm1,
 input eqz,
 output reg ldM,
 output reg ldQ,
 output reg ldA,
 output reg clrA,
 output reg clrQ,
 output reg clr_q1,
 output reg shift,
 output reg addsub,
 output reg decr,
 output reg ldcnt,
 output reg done
);
 reg [2:0] state;
 parameter IDLE=3'b000, LOAD=3'b001, CHECK=3'b010, ADD=3'b011, SUB=3'b100, SHIFT=3'b101, DONE=3'b110;
 always @(posedge clk) begin
  case(state)
   IDLE: if(start) state <= LOAD;
   LOAD: state <= CHECK;
   CHECK: if(eqz) state <= DONE;
          else if ({q0,qm1}==2'b01) state <= ADD;
          else if ({q0,qm1}==2'b10) state <= SUB;
          else state <= SHIFT;
   ADD: state <= SHIFT;
   SUB: state <= SHIFT;
   SHIFT: state <= CHECK;
   DONE: state <= IDLE;
   default: state <= IDLE;
  endcase
 end
 always @(*) begin
  ldM=0; ldQ=0; ldA=0; clrA=0; clrQ=0; clr_q1=0; shift=0; addsub=0; decr=0; ldcnt=0; done=0;
  case(state)
   IDLE: begin clrA=1; clrQ=1; clr_q1=1; end
   LOAD: begin ldM=1; ldQ=1; ldcnt=1; end
   ADD:  begin ldA=1; addsub=1; end
   SUB:  begin ldA=1; addsub=0; end
   SHIFT: begin shift=1; decr=1; end
   DONE: done=1;
  endcase
 end
endmodule

Booth algorithm/booth_datapath.v
module booth_datapath(
 input clk,
 input ldM,
 input ldQ,
 input ldA,
 input clrA,
 input clrQ,
 input clr_q1,
 input shift,
 input addsub,
 input decr,
 input ldcnt,
 input [15:0] M_in,
 input [15:0] Q_in,
 output reg [15:0] A,
 output reg [15:0] Q,
 output reg [15:0] M,
 output reg q_minus1,
 output eqz
);
 reg [4:0] count;
 wire [15:0] alu_out;
 reg [32:0] big_old;
 assign eqz = (count == 5'd0);
 assign alu_out = addsub ? (A + M) : (A - M);
 always @(*) big_old = {A, Q, q_minus1};
 always @(posedge clk) begin
  if (ldcnt) count <= 5'd16;
  else if (decr) count <= count - 1;
  if (ldM) M <= M_in;
  if (clrQ) Q <= 16'h0;
  else if (ldQ) Q <= Q_in;
  if (clrA) A <= 16'h0;
  else if (ldA) A <= alu_out;
  if (clr_q1) q_minus1 <= 1'b0;
  if (shift) begin
   {A, Q, q_minus1} <= {A[15], big_old[32:1]};
  end
 end
endmodule

Booth algorithm/booth_tb.v
`timescale 1ns/1ps
module booth_tb;
 reg clk;
 reg start;
 reg signed [15:0] M_in;
 reg signed [15:0] Q_in;
 wire [15:0] A;
 wire [15:0] Q;
 wire [15:0] M;
 wire q_minus1;
 wire eqz;
 wire done;
 wire ldM, ldQ, ldA, clrA, clrQ, clr_q1, shift, addsub, decr, ldcnt;
 booth_datapath DP(
  .clk(clk), .ldM(ldM), .ldQ(ldQ), .ldA(ldA), .clrA(clrA), .clrQ(clrQ),
  .clr_q1(clr_q1), .shift(shift), .addsub(addsub), .decr(decr), .ldcnt(ldcnt),
  .M_in(M_in), .Q_in(Q_in), .A(A), .Q(Q), .M(M), .q_minus1(q_minus1), .eqz(eqz)
 );
 booth_controller CU(
  .clk(clk), .start(start), .q0(Q[0]), .qm1(q_minus1), .eqz(eqz),
  .ldM(ldM), .ldQ(ldQ), .ldA(ldA), .clrA(clrA), .clrQ(clrQ), .clr_q1(clr_q1),
  .shift(shift), .addsub(addsub), .decr(decr), .ldcnt(ldcnt), .done(done)
 );
 initial clk = 0;
 always #5 clk = ~clk;
 initial begin
  $dumpfile("booth.vcd");
  $dumpvars(0, booth_tb);
  run_test(3,2,1);
  run_test(-4,5,2);
  run_test(7,-3,3);
  run_test(-6,-2,4);
  run_test(8,0,5);
  $finish;
 end
 task run_test;
  input signed [15:0] m;
  input signed [15:0] q;
  input integer id;
  integer timeout;
  begin
   M_in = m;
   Q_in = q;
   start = 1;
   @(posedge clk);
   start = 0;
   timeout = 0;
   while (!done && timeout < 1000) begin @(posedge clk); timeout = timeout + 1; end
   if (timeout >= 1000) $display("TEST %0d TIMEOUT M=%0d Q=%0d", id, m, q);
   else begin
    @(posedge clk);
    $display("TEST %0d M=%0d Q=%0d PRODUCT(dec)=%0d PRODUCT(hex)=%h", id, m, q, $signed({A,Q}), {A,Q});
   end
  end
 endtask
endmodule

Booth algorithm/booth.vcd
$date
	Thu Sep 04 18:30:51 2025
$end
$version
	Icarus Verilog
$end
$timescale
	1ps
$end
$scope module booth_tb $end
$var wire 16 ! A [15:0] $end
$var wire 16 " M [15:0] $end
$var wire 16 # Q [15:0] $end
$var wire 1 $ addsub $end
$var wire 1 % clrA $end
$var wire 1 & clrQ $end
$var wire 1 ' clr_q1 $end
$var wire 1 ( decr $end
$var wire 1 ) done $end
$var wire 1 * eqz $end
$var wire 1 + ldA $end
$var wire 1 , ldM $end
$var wire 1 - ldQ $end
$var wire 1 . ldcnt $end
$var wire 1 / q_minus1 $end
$var wire 1 0 shift $end
$var reg 16 1 M_in [15:0] $end
$var reg 16 2 Q_in [15:0] $end
$var reg 1 3 clk $end
$var reg 1 4 start $end
$scope module DP $end
$var wire 16 5 M_in [15:0] $end
$var wire 16 6 Q_in [15:0] $end
$var wire 1 $ addsub $end
$var wire 16 7 alu_out [15:0] $end
$var wire 1 8 clk $end
$var wire 1 % clrA $end
$var wire 1 & clrQ $end
$var wire 1 ' clr_q1 $end
$var wire 1 ( decr $end
$var wire 1 * eqz $end
$var wire 1 + ldA $end
$var wire 1 , ldM $end
$var wire 1 - ldQ $end
$var wire 1 . ldcnt $end
$var wire 1 0 shift $end
$var reg 16 9 A [15:0] $end
$var reg 16 : M [15:0] $end
$var reg 16 ; Q [15:0] $end
$var reg 33 < big_old [32:0] $end
$var reg 5 = count [4:0] $end
$var reg 1 > q_minus1 $end
$upscope $end
$scope module CU $end
$var wire 1 8 clk $end
$var wire 1 * eqz $end
$var wire 1 ? q0 $end
$var wire 1 / qm1 $end
$var wire 1 @ start $end
$var reg 1 A addsub $end
$var reg 1 B clrA $end
$var reg 1 C clrQ $end
$var reg 1 D clr_q1 $end
$var reg 1 E decr $end
$var reg 1 F done $end
$var reg 1 G ldA $end
$var reg 1 H ldM $end
$var reg 1 I ldQ $end
$var reg 1 J ldcnt $end
$var reg 1 K shift $end
$var reg 3 L state [2:0] $end
$upscope $end
$scope task run_test $end
$var integer 32 M id [31:0] $end
$var reg 16 N m [15:0] $end
$var reg 16 O q [15:0] $end
$var integer 32 P timeout [31:0] $end
$upscope $end
$upscope $end
$enddefinitions $end
#0
$dumpvars
bx P
b10 O
b11 N
b1 M
bx L
xK
xJ
xI
xH
xG
xF
xE
xD
xC
xB
xA
1@
x?
x>
bx =
bx <
bx ;
bx :
bx 9
08
bx 7
b10 6
b11 5
14
03
b10 2
b11 1
x0
x/
x.
x-
x,
x+
x*
x)
x(
x'
x&
x%
x$
bx #
bx "
bx !
$end
#5000
0F
0)
0J
0.
0E
0(
0A
0$
0K
00
1D
1'
1C
1&
1B
1%
0G
0+
0I
0-
0H
0,
b0 L
b0 P
04
0@
13
18
#10000
03
08
#15000
b0 <
0?
0>
0/
b0 9
b0 !
b0 ;
b0 #
14
1@
b101 2
b101 6
b1111111111111100 1
b1111111111111100 5
b10 M
b101 O
b1111111111111100 N
13
18
#20000
03
08
#25000
04
0@
13
18
#30000
03
08
#35000
b1 P
13
18
#40000
03
08
#45000
b10 P
13
18
#50000
03
08
#55000
b11 P
13
18
#60000
03
08
#65000
b100 P
13
18
#70000
03
08
#75000
b101 P
13
18
#80000
03
08
#85000
b110 P
13
18
#90000
03
08
#95000
b111 P
13
18
#100000
03
08
#105000
b1000 P
13
18
#110000
03
08
#115000
b1001 P
13
18
#120000
03
08
#125000
b1010 P
13
18
#130000
03
08
#135000
b1011 P
13
18
#140000
03
08
#145000
b1100 P
13
18
#150000
03
08
#155000
b1101 P
13
18
#160000
03
08
#165000
b1110 P
13
18
#170000
03
08
#175000
b1111 P
13
18
#180000
03
08
#185000
b10000 P
13
18
#190000
03
08
#195000
b10001 P
13
18
#200000
03
08
#205000
b10010 P
13
18
#210000
03
08
#215000
b10011 P
13
18
#220000
03
08
#225000
b10100 P
13
18
#230000
03
08
#235000
b10101 P
13
18
#240000
03
08
#245000
b10110 P
13
18
#250000
03
08
#255000
b10111 P
13
18
#260000
03
08
#265000
b11000 P
13
18
#270000
03
08
#275000
b11001 P
13
18
#280000
03
08
#285000
b11010 P
13
18
#290000
03
08
#295000
b11011 P
13
18
#300000
03
08
#305000
b11100 P
13
18
#310000
03
08
#315000
b11101 P
13
18
#320000
03
08
#325000
b11110 P
13
18
#330000
03
08
#335000
b11111 P
13
18
#340000
03
08
#345000
b100000 P
13
18
#350000
03
08
#355000
b100001 P
13
18
#360000
03
08
#365000
b100010 P
13
18
#370000
03
08
#375000
b100011 P
13
18
#380000
03
08
#385000
b100100 P
13
18
#390000
03
08
#395000
b100101 P
13
18
#400000
03
08
#405000
b100110 P
13
18
#410000
03
08
#415000
b100111 P
13
18
#420000
03
08
#425000
b101000 P
13
18
#430000
03
08
#435000
b101001 P
13
18
#440000
03
08
#445000
b101010 P
13
18
#450000
03
08
#455000
b101011 P
13
18
#460000
03
08
#465000
b101100 P
13
18
#470000
03
08
#475000
b101101 P
13
18
#480000
03
08
#485000
b101110 P
13
18
#490000
03
08
#495000
b101111 P
13
18
#500000
03
08
#505000
b110000 P
13
18
#510000
03
08
#515000
b110001 P
13
18
#520000
03
08
#525000
b110010 P
13
18
#530000
03
08
#535000
b110011 P
13
18
#540000
03
08
#545000
b110100 P
13
18
#550000
03
08
#555000
b110101 P
13
18
#560000
03
08
#565000
b110110 P
13
18
#570000
03
08
#575000
b110111 P
13
18
#580000
03
08
#585000
b111000 P
13
18
#590000
03
08
#595000
b111001 P
13
18
#600000
03
08
#605000
b111010 P
13
18
#610000
03
08
#615000
b111011 P
13
18
#620000
03
08
#625000
b111100 P
13
18
#630000
03
08
#635000
b111101 P
13
18
#640000
03
08
#645000
b111110 P
13
18
#650000
03
08
#655000
b111111 P
13
18
#660000
03
08
#665000
b1000000 P
13
18
#670000
03
08
#675000
b1000001 P
13
18
#680000
03
08
#685000
b1000010 P
13
18
#690000
03
08
#695000
b1000011 P
13
18
#700000
03
08
#705000
b1000100 P
13
18
#710000
03
08
#715000
b1000101 P
13
18
#720000
03
08
#725000
b1000110 P
13
18
#730000
03
08
#735000
b1000111 P
13
18
#740000
03
08
#745000
b1001000 P
13
18
#750000
03
08
#755000
b1001001 P
13
18
#760000
03
08
#765000
b1001010 P
13
18
#770000
03
08
#775000
b1001011 P
13
18
#780000
03
08
#785000
b1001100 P
13
18
#790000
03
08
#795000
b1001101 P
13
18
#800000
03
08
#805000
b1001110 P
13
18
#810000
03
08
#815000
b1001111 P
13
18
#820000
03
08
#825000
b1010000 P
13
18
#830000
03
08
#835000
b1010001 P
13
18
#840000
03
08
#845000
b1010010 P
13
18
#850000
03
08
#855000
b1010011 P
13
18
#860000
03
08
#865000
b1010100 P
13
18
#870000
03
08
#875000
b1010101 P
13
18
#880000
03
08
#885000
b1010110 P
13
18
#890000
03
08
#895000
b1010111 P
13
18
#900000
03
08
#905000
b1011000 P
13
18
#910000
03
08
#915000
b1011001 P
13
18
#920000
03
08
#925000
b1011010 P
13
18
#930000
03
08
#935000
b1011011 P
13
18
#940000
03
08
#945000
b1011100 P
13
18
#950000
03
08
#955000
b1011101 P
13
18
#960000
03
08
#965000
b1011110 P
13
18
#970000
03
08
#975000
b1011111 P
13
18
#980000
03
08
#985000
b1100000 P
13
18
#990000
03
08
#995000
b1100001 P
13
18
#1000000
03
08
#1005000
b1100010 P
13
18
#1010000
03
08
#1015000
b1100011 P
13
18
#1020000
03
08
#1025000
b1100100 P
13
18
#1030000
03
08
#1035000
b1100101 P
13
18
#1040000
03
08
#1045000
b1100110 P
13
18
#1050000
03
08
#1055000
b1100111 P
13
18
#1060000
03
08
#1065000
b1101000 P
13
18
#1070000
03
08
#1075000
b1101001 P
13
18
#1080000
03
08
#1085000
b1101010 P
13
18
#1090000
03
08
#1095000
b1101011 P
13
18
#1100000
03
08
#1105000
b1101100 P
13
18
#1110000
03
08
#1115000
b1101101 P
13
18
#1120000
03
08
#1125000
b1101110 P
13
18
#1130000
03
08
#1135000
b1101111 P
13
18
#1140000
03
08
#1145000
b1110000 P
13
18
#1150000
03
08
#1155000
b1110001 P
13
18
#1160000
03
08
#1165000
b1110010 P
13
18
#1170000
03
08
#1175000
b1110011 P
13
18
#1180000
03
08
#1185000
b1110100 P
13
18
#1190000
03
08
#1195000
b1110101 P
13
18
#1200000
03
08
#1205000
b1110110 P
13
18
#1210000
03
08
#1215000
b1110111 P
13
18
#1220000
03
08
#1225000
b1111000 P
13
18
#1230000
03
08
#1235000
b1111001 P
13
18
#1240000
03
08
#1245000
b1111010 P
13
18
#1250000
03
08
#1255000
b1111011 P
13
18
#1260000
03
08
#1265000
b1111100 P
13
18
#1270000
03
08
#1275000
b1111101 P
13
18
#1280000
03
08
#1285000
b1111110 P
13
18
#1290000
03
08
#1295000
b1111111 P
13
18
#1300000
03
08
#1305000
b10000000 P
13
18
#1310000
03
08
#1315000
b10000001 P
13
18
#1320000
03
08
#1325000
b10000010 P
13
18
#1330000
03
08
#1335000
b10000011 P
13
18
#1340000
03
08
#1345000
b10000100 P
13
18
#1350000
03
08
#1355000
b10000101 P
13
18
#1360000
03
08
#1365000
b10000110 P
13
18
#1370000
03
08
#1375000
b10000111 P
13
18
#1380000
03
08
#1385000
b10001000 P
13
18
#1390000
03
08
#1395000
b10001001 P
13
18
#1400000
03
08
#1405000
b10001010 P
13
18
#1410000
03
08
#1415000
b10001011 P
13
18
#1420000
03
08
#1425000
b10001100 P
13
18
#1430000
03
08
#1435000
b10001101 P
13
18
#1440000
03
08
#1445000
b10001110 P
13
18
#1450000
03
08
#1455000
b10001111 P
13
18
#1460000
03
08
#1465000
b10010000 P
13
18
#1470000
03
08
#1475000
b10010001 P
13
18
#1480000
03
08
#1485000
b10010010 P
13
18
#1490000
03
08
#1495000
b10010011 P
13
18
#1500000
03
08
#1505000
b10010100 P
13
18
#1510000
03
08
#1515000
b10010101 P
13
18
#1520000
03
08
#1525000
b10010110 P
13
18
#1530000
03
08
#1535000
b10010111 P
13
18
#1540000
03
08
#1545000
b10011000 P
13
18
#1550000
03
08
#1555000
b10011001 P
13
18
#1560000
03
08
#1565000
b10011010 P
13
18
#1570000
03
08
#1575000
b10011011 P
13
18
#1580000
03
08
#1585000
b10011100 P
13
18
#1590000
03
08
#1595000
b10011101 P
13
18
#1600000
03
08
#1605000
b10011110 P
13
18
#1610000
03
08
#1615000
b10011111 P
13
18
#1620000
03
08
#1625000
b10100000 P
13
18
#1630000
03
08
#1635000
b10100001 P
13
18
#1640000
03
08
#1645000
b10100010 P
13
18
#1650000
03
08
#1655000
b10100011 P
13
18
#1660000
03
08
#1665000
b10100100 P
13
18
#1670000
03
08
#1675000
b10100101 P
13
18
#1680000
03
08
#1685000
b10100110 P
13
18
#1690000
03
08
#1695000
b10100111 P
13
18
#1700000
03
08
#1705000
b10101000 P
13
18
#1710000
03
08
#1715000
b10101001 P
13
18
#1720000
03
08
#1725000
b10101010 P
13
18
#1730000
03
08
#1735000
b10101011 P
13
18
#1740000
03
08
#1745000
b10101100 P
13
18
#1750000
03
08
#1755000
b10101101 P
13
18
#1760000
03
08
#1765000
b10101110 P
13
18
#1770000
03
08
#1775000
b10101111 P
13
18
#1780000
03
08
#1785000
b10110000 P
13
18
#1790000
03
08
#1795000
b10110001 P
13
18
#1800000
03
08
#1805000
b10110010 P
13
18
#1810000
03
08
#1815000
b10110011 P
13
18
#1820000
03
08
#1825000
b10110100 P
13
18
#1830000
03
08
#1835000
b10110101 P
13
18
#1840000
03
08
#1845000
b10110110 P
13
18
#1850000
03
08
#1855000
b10110111 P
13
18
#1860000
03
08
#1865000
b10111000 P
13
18
#1870000
03
08
#1875000
b10111001 P
13
18
#1880000
03
08
#1885000
b10111010 P
13
18
#1890000
03
08
#1895000
b10111011 P
13
18
#1900000
03
08
#1905000
b10111100 P
13
18
#1910000
03
08
#1915000
b10111101 P
13
18
#1920000
03
08
#1925000
b10111110 P
13
18
#1930000
03
08
#1935000
b10111111 P
13
18
#1940000
03
08
#1945000
b11000000 P
13
18
#1950000
03
08
#1955000
b11000001 P
13
18
#1960000
03
08
#1965000
b11000010 P
13
18
#1970000
03
08
#1975000
b11000011 P
13
18
#1980000
03
08
#1985000
b11000100 P
13
18
#1990000
03
08
#1995000
b11000101 P
13
18
#2000000
03
08
#2005000
b11000110 P
13
18
#2010000
03
08
#2015000
b11000111 P
13
18
#2020000
03
08
#2025000
b11001000 P
13
18
#2030000
03
08
#2035000
b11001001 P
13
18
#2040000
03
08
#2045000
b11001010 P
13
18
#2050000
03
08
#2055000
b11001011 P
13
18
#2060000
03
08
#2065000
b11001100 P
13
18
#2070000
03
08
#2075000
b11001101 P
13
18
#2080000
03
08
#2085000
b11001110 P
13
18
#2090000
03
08
#2095000
b11001111 P
13
18
#2100000
03
08
#2105000
b11010000 P
13
18
#2110000
03
08
#2115000
b11010001 P
13
18
#2120000
03
08
#2125000
b11010010 P
13
18
#2130000
03
08
#2135000
b11010011 P
13
18
#2140000
03
08
#2145000
b11010100 P
13
18
#2150000
03
08
#2155000
b11010101 P
13
18
#2160000
03
08
#2165000
b11010110 P
13
18
#2170000
03
08
#2175000
b11010111 P
13
18
#2180000
03
08
#2185000
b11011000 P
13
18
#2190000
03
08
#2195000
b11011001 P
13
18
#2200000
03
08
#2205000
b11011010 P
13
18
#2210000
03
08
#2215000
b11011011 P
13
18
#2220000
03
08
#2225000
b11011100 P
13
18
#2230000
03
08
#2235000
b11011101 P
13
18
#2240000
03
08
#2245000
b11011110 P
13
18
#2250000
03
08
#2255000
b11011111 P
13
18
#2260000
03
08
#2265000
b11100000 P
13
18
#2270000
03
08
#2275000
b11100001 P
13
18
#2280000
03
08
#2285000
b11100010 P
13
18
#2290000
03
08
#2295000
b11100011 P
13
18
#2300000
03
08
#2305000
b11100100 P
13
18
#2310000
03
08
#2315000
b11100101 P
13
18
#2320000
03
08
#2325000
b11100110 P
13
18
#2330000
03
08
#2335000
b11100111 P
13
18
#2340000
03
08
#2345000
b11101000 P
13
18
#2350000
03
08
#2355000
b11101001 P
13
18
#2360000
03
08
#2365000
b11101010 P
13
18
#2370000
03
08
#2375000
b11101011 P
13
18
#2380000
03
08
#2385000
b11101100 P
13
18
#2390000
03
08
#2395000
b11101101 P
13
18
#2400000
03
08
#2405000
b11101110 P
13
18
#2410000
03
08
#2415000
b11101111 P
13
18
#2420000
03
08
#2425000
b11110000 P
13
18
#2430000
03
08
#2435000
b11110001 P
13
18
#2440000
03
08
#2445000
b11110010 P
13
18
#2450000
03
08
#2455000
b11110011 P
13
18
#2460000
03
08
#2465000
b11110100 P
13
18
#2470000
03
08
#2475000
b11110101 P
13
18
#2480000
03
08
#2485000
b11110110 P
13
18
#2490000
03
08
#2495000
b11110111 P
13
18
#2500000
03
08
#2505000
b11111000 P
13
18
#2510000
03
08
#2515000
b11111001 P
13
18
#2520000
03
08
#2525000
b11111010 P
13
18
#2530000
03
08
#2535000
b11111011 P
13
18
#2540000
03
08
#2545000
b11111100 P
13
18
#2550000
03
08
#2555000
b11111101 P
13
18
#2560000
03
08
#2565000
b11111110 P
13
18
#2570000
03
08
#2575000
b11111111 P
13
18
#2580000
03
08
#2585000
b100000000 P
13
18
#2590000
03
08
#2595000
b100000001 P
13
18
#2600000
03
08
#2605000
b100000010 P
13
18
#2610000
03
08
#2615000
b100000011 P
13
18
#2620000
03
08
#2625000
b100000100 P
13
18
#2630000
03
08
#2635000
b100000101 P
13
18
#2640000
03
08
#2645000
b100000110 P
13
18
#2650000
03
08
#2655000
b100000111 P
13
18
#2660000
03
08
#2665000
b100001000 P
13
18
#2670000
03
08
#2675000
b100001001 P
13
18
#2680000
03
08
#2685000
b100001010 P
13
18
#2690000
03
08
#2695000
b100001011 P
13
18
#2700000
03
08
#2705000
b100001100 P
13
18
#2710000
03
08
#2715000
b100001101 P
13
18
#2720000
03
08
#2725000
b100001110 P
13
18
#2730000
03
08
#2735000
b100001111 P
13
18
#2740000
03
08
#2745000
b100010000 P
13
18
#2750000
03
08
#2755000
b100010001 P
13
18
#2760000
03
08
#2765000
b100010010 P
13
18
#2770000
03
08
#2775000
b100010011 P
13
18
#2780000
03
08
#2785000
b100010100 P
13
18
#2790000
03
08
#2795000
b100010101 P
13
18
#2800000
03
08
#2805000
b100010110 P
13
18
#2810000
03
08
#2815000
b100010111 P
13
18
#2820000
03
08
#2825000
b100011000 P
13
18
#2830000
03
08
#2835000
b100011001 P
13
18
#2840000
03
08
#2845000
b100011010 P
13
18
#2850000
03
08
#2855000
b100011011 P
13
18
#2860000
03
08
#2865000
b100011100 P
13
18
#2870000
03
08
#2875000
b100011101 P
13
18
#2880000
03
08
#2885000
b100011110 P
13
18
#2890000
03
08
#2895000
b100011111 P
13
18
#2900000
03
08
#2905000
b100100000 P
13
18
#2910000
03
08
#2915000
b100100001 P
13
18
#2920000
03
08
#2925000
b100100010 P
13
18
#2930000
03
08
#2935000
b100100011 P
13
18
#2940000
03
08
#2945000
b100100100 P
13
18
#2950000
03
08
#2955000
b100100101 P
13
18
#2960000
03
08
#2965000
b100100110 P
13
18
#2970000
03
08
#2975000
b100100111 P
13
18
#2980000
03
08
#2985000
b100101000 P
13
18
#2990000
03
08
#2995000
b100101001 P
13
18
#3000000
03
08
#3005000
b100101010 P
13
18
#3010000
03
08
#3015000
b100101011 P
13
18
#3020000
03
08
#3025000
b100101100 P
13
18
#3030000
03
08
#3035000
b100101101 P
13
18
#3040000
03
08
#3045000
b100101110 P
13
18
#3050000
03
08
#3055000
b100101111 P
13
18
#3060000
03
08
#3065000
b100110000 P
13
18
#3070000
03
08
#3075000
b100110001 P
13
18
#3080000
03
08
#3085000
b100110010 P
13
18
#3090000
03
08
#3095000
b100110011 P
13
18
#3100000
03
08
#3105000
b100110100 P
13
18
#3110000
03
08
#3115000
b100110101 P
13
18
#3120000
03
08
#3125000
b100110110 P
13
18
#3130000
03
08
#3135000
b100110111 P
13
18
#3140000
03
08
#3145000
b100111000 P
13
18
#3150000
03
08
#3155000
b100111001 P
13
18
#3160000
03
08
#3165000
b100111010 P
13
18
#3170000
03
08
#3175000
b100111011 P
13
18
#3180000
03
08
#3185000
b100111100 P
13
18
#3190000
03
08
#3195000
b100111101 P
13
18
#3200000
03
08
#3205000
b100111110 P
13
18
#3210000
03
08
#3215000
b100111111 P
13
18
#3220000
03
08
#3225000
b101000000 P
13
18
#3230000
03
08
#3235000
b101000001 P
13
18
#3240000
03
08
#3245000
b101000010 P
13
18
#3250000
03
08
#3255000
b101000011 P
13
18
#3260000
03
08
#3265000
b101000100 P
13
18
#3270000
03
08
#3275000
b101000101 P
13
18
#3280000
03
08
#3285000
b101000110 P
13
18
#3290000
03
08
#3295000
b101000111 P
13
18
#3300000
03
08
#3305000
b101001000 P
13
18
#3310000
03
08
#3315000
b101001001 P
13
18
#3320000
03
08
#3325000
b101001010 P
13
18
#3330000
03
08
#3335000
b101001011 P
13
18
#3340000
03
08
#3345000
b101001100 P
13
18
#3350000
03
08
#3355000
b101001101 P
13
18
#3360000
03
08
#3365000
b101001110 P
13
18
#3370000
03
08
#3375000
b101001111 P
13
18
#3380000
03
08
#3385000
b101010000 P
13
18
#3390000
03
08
#3395000
b101010001 P
13
18
#3400000
03
08
#3405000
b101010010 P
13
18
#3410000
03
08
#3415000
b101010011 P
13
18
#3420000
03
08
#3425000
b101010100 P
13
18
#3430000
03
08
#3435000
b101010101 P
13
18
#3440000
03
08
#3445000
b101010110 P
13
18
#3450000
03
08
#3455000
b101010111 P
13
18
#3460000
03
08
#3465000
b101011000 P
13
18
#3470000
03
08
#3475000
b101011001 P
13
18
#3480000
03
08
#3485000
b101011010 P
13
18
#3490000
03
08
#3495000
b101011011 P
13
18
#3500000
03
08
#3505000
b101011100 P
13
18
#3510000
03
08
#3515000
b101011101 P
13
18
#3520000
03
08
#3525000
b101011110 P
13
18
#3530000
03
08
#3535000
b101011111 P
13
18
#3540000
03
08
#3545000
b101100000 P
13
18
#3550000
03
08
#3555000
b101100001 P
13
18
#3560000
03
08
#3565000
b101100010 P
13
18
#3570000
03
08
#3575000
b101100011 P
13
18
#3580000
03
08
#3585000
b101100100 P
13
18
#3590000
03
08
#3595000
b101100101 P
13
18
#3600000
03
08
#3605000
b101100110 P
13
18
#3610000
03
08
#3615000
b101100111 P
13
18
#3620000
03
08
#3625000
b101101000 P
13
18
#3630000
03
08
#3635000
b101101001 P
13
18
#3640000
03
08
#3645000
b101101010 P
13
18
#3650000
03
08
#3655000
b101101011 P
13
18
#3660000
03
08
#3665000
b101101100 P
13
18
#3670000
03
08
#3675000
b101101101 P
13
18
#3680000
03
08
#3685000
b101101110 P
13
18
#3690000
03
08
#3695000
b101101111 P
13
18
#3700000
03
08
#3705000
b101110000 P
13
18
#3710000
03
08
#3715000
b101110001 P
13
18
#3720000
03
08
#3725000
b101110010 P
13
18
#3730000
03
08
#3735000
b101110011 P
13
18
#3740000
03
08
#3745000
b101110100 P
13
18
#3750000
03
08
#3755000
b101110101 P
13
18
#3760000
03
08
#3765000
b101110110 P
13
18
#3770000
03
08
#3775000
b101110111 P
13
18
#3780000
03
08
#3785000
b101111000 P
13
18
#3790000
03
08
#3795000
b101111001 P
13
18
#3800000
03
08
#3805000
b101111010 P
13
18
#3810000
03
08
#3815000
b101111011 P
13
18
#3820000
03
08
#3825000
b101111100 P
13
18
#3830000
03
08
#3835000
b101111101 P
13
18
#3840000
03
08
#3845000
b101111110 P
13
18
#3850000
03
08
#3855000
b101111111 P
13
18
#3860000
03
08
#3865000
b110000000 P
13
18
#3870000
03
08
#3875000
b110000001 P
13
18
#3880000
03
08
#3885000
b110000010 P
13
18
#3890000
03
08
#3895000
b110000011 P
13
18
#3900000
03
08
#3905000
b110000100 P
13
18
#3910000
03
08
#3915000
b110000101 P
13
18
#3920000
03
08
#3925000
b110000110 P
13
18
#3930000
03
08
#3935000
b110000111 P
13
18
#3940000
03
08
#3945000
b110001000 P
13
18
#3950000
03
08
#3955000
b110001001 P
13
18
#3960000
03
08
#3965000
b110001010 P
13
18
#3970000
03
08
#3975000
b110001011 P
13
18
#3980000
03
08
#3985000
b110001100 P
13
18
#3990000
03
08
#3995000
b110001101 P
13
18
#4000000
03
08
#4005000
b110001110 P
13
18
#4010000
03
08
#4015000
b110001111 P
13
18
#4020000
03
08
#4025000
b110010000 P
13
18
#4030000
03
08
#4035000
b110010001 P
13
18
#4040000
03
08
#4045000
b110010010 P
13
18
#4050000
03
08
#4055000
b110010011 P
13
18
#4060000
03
08
#4065000
b110010100 P
13
18
#4070000
03
08
#4075000
b110010101 P
13
18
#4080000
03
08
#4085000
b110010110 P
13
18
#4090000
03
08
#4095000
b110010111 P
13
18
#4100000
03
08
#4105000
b110011000 P
13
18
#4110000
03
08
#4115000
b110011001 P
13
18
#4120000
03
08
#4125000
b110011010 P
13
18
#4130000
03
08
#4135000
b110011011 P
13
18
#4140000
03
08
#4145000
b110011100 P
13
18
#4150000
03
08
#4155000
b110011101 P
13
18
#4160000
03
08
#4165000
b110011110 P
13
18
#4170000
03
08
#4175000
b110011111 P
13
18
#4180000
03
08
#4185000
b110100000 P
13
18
#4190000
03
08
#4195000
b110100001 P
13
18
#4200000
03
08
#4205000
b110100010 P
13
18
#4210000
03
08
#4215000
b110100011 P
13
18
#4220000
03
08
#4225000
b110100100 P
13
18
#4230000
03
08
#4235000
b110100101 P
13
18
#4240000
03
08
#4245000
b110100110 P
13
18
#4250000
03
08
#4255000
b110100111 P
13
18
#4260000
03
08
#4265000
b110101000 P
13
18
#4270000
03
08
#4275000
b110101001 P
13
18
#4280000
03
08
#4285000
b110101010 P
13
18
#4290000
03
08
#4295000
b110101011 P
13
18
#4300000
03
08
#4305000
b110101100 P
13
18
#4310000
03
08
#4315000
b110101101 P
13
18
#4320000
03
08
#4325000
b110101110 P
13
18
#4330000
03
08
#4335000
b110101111 P
13
18
#4340000
03
08
#4345000
b110110000 P
13
18
#4350000
03
08
#4355000
b110110001 P
13
18
#4360000
03
08
#4365000
b110110010 P
13
18
#4370000
03
08
#4375000
b110110011 P
13
18
#4380000
03
08
#4385000
b110110100 P
13
18
#4390000
03
08
#4395000
b110110101 P
13
18
#4400000
03
08
#4405000
b110110110 P
13
18
#4410000
03
08
#4415000
b110110111 P
13
18
#4420000
03
08
#4425000
b110111000 P
13
18
#4430000
03
08
#4435000
b110111001 P
13
18
#4440000
03
08
#4445000
b110111010 P
13
18
#4450000
03
08
#4455000
b110111011 P
13
18
#4460000
03
08
#4465000
b110111100 P
13
18
#4470000
03
08
#4475000
b110111101 P
13
18
#4480000
03
08
#4485000
b110111110 P
13
18
#4490000
03
08
#4495000
b110111111 P
13
18
#4500000
03
08
#4505000
b111000000 P
13
18
#4510000
03
08
#4515000
b111000001 P
13
18
#4520000
03
08
#4525000
b111000010 P
13
18
#4530000
03
08
#4535000
b111000011 P
13
18
#4540000
03
08
#4545000
b111000100 P
13
18
#4550000
03
08
#4555000
b111000101 P
13
18
#4560000
03
08
#4565000
b111000110 P
13
18
#4570000
03
08
#4575000
b111000111 P
13
18
#4580000
03
08
#4585000
b111001000 P
13
18
#4590000
03
08
#4595000
b111001001 P
13
18
#4600000
03
08
#4605000
b111001010 P
13
18
#4610000
03
08
#4615000
b111001011 P
13
18
#4620000
03
08
#4625000
b111001100 P
13
18
#4630000
03
08
#4635000
b111001101 P
13
18
#4640000
03
08
#4645000
b111001110 P
13
18
#4650000
03
08
#4655000
b111001111 P
13
18
#4660000
03
08
