ring_counter/ring_counter_8bit.v
module ring_counter_8bit (
    input  wire clk,
    input  wire rst,       
    output reg  [7:0] out
);

    always @(posedge clk or posedge rst) begin
        if (rst) begin
            
            out <= 8'b00000001;
        end else begin
            
            out <= { out[6:0], out[7] };
        end
    end

endmodule

ring_counter/tb_ring_counter_8bit.v
`timescale 1ns/1ps
module tb_ring_counter_8bit;
    reg clk;
    reg rst;
    wire [7:0] out;

    // DUT
    ring_counter_8bit dut (
        .clk(clk),
        .rst(rst),
        .out(out)
    );

    
    initial clk = 0;
    always #5 clk = ~clk;

    initial begin
        $dumpfile("ringcounter8bit.vcd");
        $dumpvars(0, tb_ring_counter_8bit);

        
        rst = 1; #12;
        rst = 0;

        
        #200;

        $finish;
    end

    initial begin
        $monitor("%0t  clk=%b  rst=%b  out=%b", $time, clk, rst, out);
    end
endmodule

ring_counter/ringcounter8bit.vcd
$date
	Fri Aug 08 22:15:32 2025
$end
$version
	Icarus Verilog
$end
$timescale
	1ps
$end
$scope module tb_ring_counter_8bit $end
$var wire 8 ! out [7:0] $end
$var reg 1 " clk $end
$var reg 1 # rst $end
$scope module dut $end
$var wire 1 $ clk $end
$var wire 1 % rst $end
$var reg 8 & out [7:0] $end
$upscope $end
$upscope $end
$enddefinitions $end
#0
$dumpvars
b1 &
1%
0$
1#
0"
b1 !
$end
#5000
1"
1$
#10000
0"
0$
#12000
0#
0%
#15000
b10 &
b10 !
1"
1$
#20000
0"
0$
#25000
b100 &
b100 !
1"
1$
#30000
0"
0$
#35000
b1000 &
b1000 !
1"
1$
#40000
0"
0$
#45000
b10000 &
b10000 !
1"
1$
#50000
0"
0$
#55000
b100000 &
b100000 !
1"
1$
#60000
0"
0$
#65000
b1000000 &
b1000000 !
1"
1$
#70000
0"
0$
#75000
b10000000 &
b10000000 !
1"
1$
#80000
0"
0$
#85000
b1 &
b1 !
1"
1$
#90000
0"
0$
#95000
b10 &
b10 !
1"
1$
#100000
0"
0$
#105000
b100 &
b100 !
1"
1$
#110000
0"
0$
#115000
b1000 &
b1000 !
1"
1$
#120000
0"
0$
#125000
b10000 &
b10000 !
1"
1$
#130000
0"
0$
#135000
b100000 &
b100000 !
1"
1$
#140000
0"
0$
#145000
b1000000 &
b1000000 !
1"
1$
#150000
0"
0$
#155000
b10000000 &
b10000000 !
1"
1$
#160000
0"
0$
#165000
b1 &
b1 !
1"
1$
#170000
0"
0$
#175000
b10 &
b10 !
1"
1$
#180000
0"
0$
#185000
b100 &
b100 !
1"
1$
#190000
0"
0$
#195000
b1000 &
b1000 !
1"
1$
#200000
0"
0$
#205000
b10000 &
b10000 !
1"
1$
