FSM/traffic_lights.v
module traffic_lights(clk, reset, lights);
    input clk, reset;
    output reg [2:0] lights;

    // State encoding
    parameter S0 = 2'b00, S1 = 2'b01, S2 = 2'b10;

    // Light encoding
    parameter RED = 3'b100, GREEN = 3'b101, YELLOW = 3'b001;

    reg [1:0] state, next_state;

    // State Register
    always @(posedge clk or posedge reset) begin
        if (reset)
            state <= S0;
        else
            state <= next_state;
    end

    // Next State and Output Logic
    always @(*) begin
        case (state)
            S0: begin
                lights = RED;
                next_state = S1;
            end
            S1: begin
                lights = GREEN;
                next_state = S2;
            end
            S2: begin
                lights = YELLOW;
                next_state = S0;
            end
            default: begin
                lights = RED;
                next_state = S0;
            end
        endcase
    end
endmodule

FSM/tb_traffic_lights.v
module tb_traffic_lights;
    reg clk, reset;
    wire [2:0] lights;

    traffic_lights uut (.clk(clk), .reset(reset), .lights(lights));

    initial begin
        $dumpfile("trafficlights.vcd");
        $dumpvars(0, tb_traffic_lights);

        clk = 0;
        reset = 1;
        #10 reset = 0;

        #200 $finish;
    end

    always #5 clk = ~clk;
endmodule

FSM/trafficlights.vcd
$date
	Thu Aug 28 10:38:23 2025
$end
$version
	Icarus Verilog
$end
$timescale
	1s
$end
$scope module tb_traffic_lights $end
$var wire 3 ! lights [2:0] $end
$var reg 1 " clk $end
$var reg 1 # reset $end
$scope module uut $end
$var wire 1 $ clk $end
$var wire 1 % reset $end
$var reg 3 & lights [2:0] $end
$var reg 2 ' next_state [1:0] $end
$var reg 2 ( state [1:0] $end
$upscope $end
$upscope $end
$enddefinitions $end
#0
$dumpvars
b0 (
b1 '
b100 &
1%
0$
1#
0"
b100 !
$end
#5
1"
1$
#10
0"
0$
0#
0%
#15
b10 '
b101 &
b101 !
b1 (
1"
1$
#20
0"
0$
#25
b0 '
b1 &
b1 !
b10 (
1"
1$
#30
0"
0$
#35
b1 '
b100 &
b100 !
b0 (
1"
1$
#40
0"
0$
#45
b10 '
b101 &
b101 !
b1 (
1"
1$
#50
0"
0$
#55
b0 '
b1 &
b1 !
b10 (
1"
1$
#60
0"
0$
#65
b1 '
b100 &
b100 !
b0 (
1"
1$
#70
0"
0$
#75
b10 '
b101 &
b101 !
b1 (
1"
1$
#80
0"
0$
#85
b0 '
b1 &
b1 !
b10 (
1"
1$
#90
0"
0$
#95
b1 '
b100 &
b100 !
b0 (
1"
1$
#100
0"
0$
#105
b10 '
b101 &
b101 !
b1 (
1"
1$
#110
0"
0$
#115
b0 '
b1 &
b1 !
b10 (
1"
1$
#120
0"
0$
#125
b1 '
b100 &
b100 !
b0 (
1"
1$
#130
0"
0$
#135
b10 '
b101 &
b101 !
b1 (
1"
1$
#140
0"
0$
#145
b0 '
b1 &
b1 !
b10 (
1"
1$
#150
0"
0$
#155
b1 '
b100 &
b100 !
b0 (
1"
1$
#160
0"
0$
#165
b10 '
b101 &
b101 !
b1 (
1"
1$
#170
0"
0$
#175
b0 '
b1 &
b1 !
b10 (
1"
1$
#180
0"
0$
#185
b1 '
b100 &
b100 !
b0 (
1"
1$
#190
0"
0$
#195
b10 '
b101 &
b101 !
b1 (
1"
1$
#200
0"
0$
#205
b0 '
b1 &
b1 !
b10 (
1"
1$
