GCD Algorithm/controller.v
module controller(
    input clk,
    input reset,
    input start,
    input lt,
    input gt,
    input eq,
    output reg ldA,
    output reg ldB,
    output reg selA_sub,
    output reg selB_sub,
    output reg done
);

    reg [2:0] state;
    parameter IDLE  = 3'b000,
              LOADA = 3'b001,
              LOADB = 3'b010,
              COMP  = 3'b011,
              SUBA  = 3'b100,
              SUBB  = 3'b101,
              DONE  = 3'b110;

    always @(posedge clk or posedge reset) begin
        if (reset) state <= IDLE;
        else begin
            case (state)
                IDLE:  if (start) state <= LOADA; else state <= IDLE;
                LOADA: state <= LOADB;
                LOADB: state <= COMP;
                COMP:  if (eq) state <= DONE;
                       else if (gt) state <= SUBA;
                       else state <= SUBB;
                SUBA:  state <= COMP;
                SUBB:  state <= COMP;
                DONE:  state <= DONE;
                default: state <= IDLE;
            endcase
        end
    end

    always @(*) begin
        ldA = 0;
        ldB = 0;
        selA_sub = 0;
        selB_sub = 0;
        done = 0;

        case (state)
            LOADA: begin ldA = 1; selA_sub = 0; end
            LOADB: begin ldB = 1; selB_sub = 0; end
            SUBA:  begin ldA = 1; selA_sub = 1; end
            SUBB:  begin ldB = 1; selB_sub = 1; end
            DONE:  done = 1;
            default: begin end
        endcase
    end

endmodule

GCD Algorithm/gcd_datapath.v
module GCD_datapath(
    output gt,
    output lt,
    output eq,
    output [15:0] Aout,
    output [15:0] Bout,
    input ldA,
    input ldB,
    input selA_sub,
    input selB_sub,
    input [15:0] data_in,
    input clk
);

    reg [15:0] A;
    reg [15:0] B;
    wire [15:0] subAB = A - B;
    wire [15:0] subBA = B - A;

    always @(posedge clk) begin
        if (ldA) A <= (selA_sub ? subAB : data_in);
        if (ldB) B <= (selB_sub ? subBA : data_in);
    end

    assign Aout = A;
    assign Bout = B;
    assign lt = (A < B);
    assign gt = (A > B);
    assign eq = (A == B);

endmodule

GCD Algorithm/gcd_test.v
module gcd_test;
    reg clk;
    reg reset;
    reg start;
    reg [15:0] data_in;
    wire gt, lt, eq;
    wire [15:0] Aout, Bout;
    wire ldA, ldB, selA_sub, selB_sub;
    wire done;

    GCD_datapath DP (
        .gt(gt),
        .lt(lt),
        .eq(eq),
        .Aout(Aout),
        .Bout(Bout),
        .ldA(ldA),
        .ldB(ldB),
        .selA_sub(selA_sub),
        .selB_sub(selB_sub),
        .data_in(data_in),
        .clk(clk)
    );

    controller CON (
        .clk(clk),
        .reset(reset),
        .start(start),
        .lt(lt),
        .gt(gt),
        .eq(eq),
        .ldA(ldA),
        .ldB(ldB),
        .selA_sub(selA_sub),
        .selB_sub(selB_sub),
        .done(done)
    );

    initial begin
        $dumpfile("gcd.vcd");
        $dumpvars(0, gcd_test);
        clk = 0;
        reset = 1;
        start = 0;
        data_in = 16'd0;
        #7 reset = 0;
        data_in = 16'd48;
        start = 1;
        #10 start = 0;
        #10 data_in = 16'd18;
        #300 $finish;
    end

    always #5 clk = ~clk;

    initial begin
        $monitor("t=%0t A=%0d B=%0d ldA=%b ldB=%b selA=%b selB=%b done=%b", $time, Aout, Bout, ldA, ldB, selA_sub, selB_sub, done);
    end
endmodule

GCD Algorithm/gcd.vcd
$date
	Tue Sep 02 23:02:30 2025
$end
$version
	Icarus Verilog
$end
$timescale
	1s
$end
$scope module gcd_test $end
$var wire 16 ! Aout [15:0] $end
$var wire 16 " Bout [15:0] $end
$var wire 1 # done $end
$var wire 1 $ eq $end
$var wire 1 % gt $end
$var wire 1 & ldA $end
$var wire 1 ' ldB $end
$var wire 1 ( lt $end
$var wire 1 ) selA_sub $end
$var wire 1 * selB_sub $end
$var reg 1 + clk $end
$var reg 16 , data_in [15:0] $end
$var reg 1 - reset $end
$var reg 1 . start $end
$scope module DP $end
$var wire 16 / Aout [15:0] $end
$var wire 16 0 Bout [15:0] $end
$var wire 1 1 clk $end
$var wire 16 2 data_in [15:0] $end
$var wire 1 $ eq $end
$var wire 1 % gt $end
$var wire 1 & ldA $end
$var wire 1 ' ldB $end
$var wire 1 ( lt $end
$var wire 1 ) selA_sub $end
$var wire 1 * selB_sub $end
$var wire 16 3 subAB [15:0] $end
$var wire 16 4 subBA [15:0] $end
$var reg 16 5 A [15:0] $end
$var reg 16 6 B [15:0] $end
$upscope $end
$scope module CON $end
$var wire 1 1 clk $end
$var wire 1 $ eq $end
$var wire 1 % gt $end
$var wire 1 ( lt $end
$var wire 1 7 reset $end
$var wire 1 8 start $end
$var reg 1 9 done $end
$var reg 1 : ldA $end
$var reg 1 ; ldB $end
$var reg 1 < selA_sub $end
$var reg 1 = selB_sub $end
$var reg 3 > state [2:0] $end
$upscope $end
$upscope $end
$enddefinitions $end
#0
$dumpvars
b0 >
0=
0<
0;
0:
09
08
17
bx 6
bx 5
bx 4
bx 3
b0 2
01
bx 0
bx /
0.
1-
b0 ,
0+
0*
0)
x(
0'
0&
x%
x$
0#
bx "
bx !
$end
#5
1+
11
#7
1.
18
b110000 ,
b110000 2
0-
07
#10
0+
01
#15
1:
1&
b1 >
1+
11
#17
0.
08
#20
0+
01
#25
1;
1'
0:
0&
b10 >
b110000 5
b110000 !
b110000 /
1+
11
#27
b10010 ,
b10010 2
#30
0+
01
#35
0;
0'
b11 >
b10010 6
b11110 3
b1111111111100010 4
0(
1%
0$
b10010 "
b10010 0
1+
11
#40
0+
01
#45
1<
1)
1:
1&
b100 >
1+
11
#50
0+
01
#55
0<
0)
0:
0&
b11 >
b11110 5
b1100 3
b1111111111110100 4
b11110 !
b11110 /
1+
11
#60
0+
01
#65
1<
1)
1:
1&
b100 >
1+
11
#70
0+
01
#75
0<
0)
0:
0&
b11 >
b1100 5
b1111111111111010 3
b110 4
1(
0%
b1100 !
b1100 /
1+
11
#80
0+
01
#85
1=
1*
1;
1'
b101 >
1+
11
#90
0+
01
#95
0=
0*
0;
0'
b11 >
b110 6
b110 3
b1111111111111010 4
0(
1%
b110 "
b110 0
1+
11
#100
0+
01
#105
1<
1)
1:
1&
b100 >
1+
11
#110
0+
01
#115
0<
0)
0:
0&
b11 >
b110 5
b0 3
b0 4
0%
1$
b110 !
b110 /
1+
11
#120
0+
01
#125
19
1#
b110 >
1+
11
