shift_register/shift_register_4bit.v
module shift_register_4bit (
    // Input ports
    input wire clk,      // Clock signal
    input wire rst_n,    // Active-low synchronous reset
    input wire data_in,  // Serial data input

    // Output port
    output wire data_out // Serial data output
);

    // Internal 4-bit register to hold the shifted data.
    reg [3:0] shift_reg;

    // The core logic of the shift register.
    // This block is sensitive to the positive edge of the clock
    // and the negative edge of the reset signal.
    always @(posedge clk or negedge rst_n) begin
        // On reset (rst_n is low), clear the register to all zeros.
        if (!rst_n) begin
            shift_reg <= 4'b0000;
        end
        // On the positive edge of the clock, perform the shift operation.
        else begin
            // The new value of the register is formed by concatenating
            // the lower 3 bits of the current register value with the new data_in.
            // Example: If shift_reg is 1011 and data_in is 0,
            // the new value becomes {011, 0} -> 0110.
            shift_reg <= {shift_reg[2:0], data_in};
        end
    end

    // The output is the most significant bit (MSB) of the register.
    // As data shifts in from the right (LSB), it eventually shifts out from the left (MSB).
    assign data_out = shift_reg[3];

endmodule

shift_register/tb_shift_register_4bit.v
`timescale 1ns / 1ps // Defines the time unit and precision for the simulation.

module tb_shift_register_4bit;

    // Testbench signals
    reg clk;      // Clock signal to be generated
    reg rst_n;    // Reset signal to be generated
    reg data_in;  // Data input to drive the DUT
    wire data_out; // Data output to be monitored from the DUT

    // Instantiate the Design Under Test (DUT)
    shift_register_4bit dut (
        .clk(clk),
        .rst_n(rst_n),
        .data_in(data_in),
        .data_out(data_out)
    );

    // Clock generation block
    // Creates a clock with a 10ns period (5ns high, 5ns low).
    initial begin
        clk = 0;
        forever #5 clk = ~clk; // Toggle clock every 5ns
    end

    // Main stimulus block
    initial begin
        // VCD (Value Change Dump) file generation
        $dumpfile("dump.vcd"); // Specifies the output VCD filename
        $dumpvars(0, tb_shift_register_4bit); // Dumps all variables in this module and below

        // 1. Initialize signals
        rst_n = 1'b1; // De-assert reset initially
        data_in = 1'b0;
        #10; // Wait for a moment

        // 2. Apply reset
        $display("T=%0t: Applying reset...", $time);
        rst_n = 1'b0; // Assert active-low reset
        #15; // Hold reset for 1.5 clock cycles
        rst_n = 1'b1; // De-assert reset
        $display("T=%0t: Releasing reset.", $time);
        #5;

        // 3. Drive data sequence: 1101
        $display("T=%0t: Starting data transmission: 1101", $time);

        // Send bit 1
        @(posedge clk);
        data_in = 1'b1;
        $display("T=%0t: Driving data_in = %b, Register = %b, data_out = %b", $time, data_in, dut.shift_reg, data_out);

        // Send bit 0
        @(posedge clk);
        data_in = 1'b0;
        $display("T=%0t: Driving data_in = %b, Register = %b, data_out = %b", $time, data_in, dut.shift_reg, data_out);

        // Send bit 1
        @(posedge clk);
        data_in = 1'b1;
        $display("T=%0t: Driving data_in = %b, Register = %b, data_out = %b", $time, data_in, dut.shift_reg, data_out);

        // Send bit 1
        @(posedge clk);
        data_in = 1'b1;
        $display("T=%0t: Driving data_in = %b, Register = %b, data_out = %b", $time, data_in, dut.shift_reg, data_out);

        // 4. Drive a few more clocks to see the data shift out
        @(posedge clk);
        data_in = 1'b0; // Drive 0 to flush out the register
        $display("T=%0t: Driving data_in = %b, Register = %b, data_out = %b", $time, data_in, dut.shift_reg, data_out);

        @(posedge clk);
        $display("T=%0t: Driving data_in = %b, Register = %b, data_out = %b", $time, data_in, dut.shift_reg, data_out);

        @(posedge clk);
        $display("T=%0t: Driving data_in = %b, Register = %b, data_out = %b", $time, data_in, dut.shift_reg, data_out);

        @(posedge clk);
        $display("T=%0t: Driving data_in = %b, Register = %b, data_out = %b", $time, data_in, dut.shift_reg, data_out);

        // 5. End simulation
        #20;
        $display("T=%0t: Simulation finished.", $time);
        $finish;
    end

endmodule

shift_register/dump.vcd
$date
	Wed Aug 20 22:46:35 2025
$end
$version
	Icarus Verilog
$end
$timescale
	1ps
$end
$scope module tb_shift_register_4bit $end
$var wire 1 ! data_out $end
$var reg 1 " clk $end
$var reg 1 # data_in $end
$var reg 1 $ rst_n $end
$scope module dut $end
$var wire 1 % clk $end
$var wire 1 & data_in $end
$var wire 1 ! data_out $end
$var wire 1 ' rst_n $end
$var reg 4 ( shift_reg [3:0] $end
$upscope $end
$upscope $end
$enddefinitions $end
#0
$dumpvars
bx (
1'
0&
0%
1$
0#
0"
x!
$end
#5000
bx0 (
1"
1%
#10000
0!
b0 (
0"
0%
0$
0'
#15000
1"
1%
#20000
0"
0%
#25000
1"
1%
1$
1'
#30000
0"
0%
#35000
b1 (
1#
1&
1"
1%
#40000
0"
0%
#45000
b10 (
0#
0&
1"
1%
#50000
0"
0%
#55000
b101 (
1#
1&
1"
1%
#60000
0"
0%
#65000
1!
b1011 (
1"
1%
#70000
0"
0%
#75000
0!
b110 (
0#
0&
1"
1%
#80000
0"
0%
#85000
1!
b1100 (
1"
1%
#90000
0"
0%
#95000
b1000 (
1"
1%
#100000
0"
0%
#105000
0!
b0 (
1"
1%
